zgulde/__init__.py
zgulde/__main__.py
zgulde/ds_imports.py
zgulde/extend_pandas.py
zgulde/google_sheet_reader.py
zgulde/hl_matches.py
zgulde/test_util.py
zgulde/util.py
zgulde/contact_info/__init__.py
zgulde/contact_info/__main__.py
zgulde/ds_util/__init__.py
zgulde/ds_util/modeling.py
zgulde/ds_util/nlp.py
zgulde/ds_util/plotting.py
zgulde/em/__init__.py
zgulde/em/__main__.py
zgulde/em/test_extract_markdown.py
zgulde/flashcards/__init__.py
zgulde/flashcards/__main__.py
zgulde/flashcards/test_flashcards.py
zgulde/gitlog/__init__.py
zgulde/gitlog/__main__.py
zgulde/gitlog/gitlog.py
zgulde/gitlog/to_csv.py
zgulde-0.0.41.dist-info/LICENSE
zgulde-0.0.41.dist-info/METADATA
zgulde-0.0.41.dist-info/WHEEL
zgulde-0.0.41.dist-info/top_level.txt
zgulde-0.0.41.dist-info/RECORD
