Metadata-Version: 2.1
Name: zgulde
Version: 0.0.41
Summary: A Small Person Utility Library
Home-page: https://github.com/zgulde/zgulde-python
Author: Zach Gulde
Author-email: zachgulde@gmail.com
License: UNKNOWN
Platform: UNKNOWN
Classifier: Programming Language :: Python :: 3
Classifier: License :: OSI Approved :: MIT License
Classifier: Operating System :: OS Independent
Requires-Dist: pandas (>=1.0.1)
Requires-Dist: matplotlib (>=2.2.0)
Requires-Dist: scikit-learn (>=0.22.1)
Requires-Dist: GitPython (==3.1.0)
